{
  "$schema": "http://json-schema.org/draft-07/schema#",
  "type": "object",
  "required": ["spreadsheetId"],
  "properties": {
    "spreadsheetId": {
      "type": "string",
      "description": "Spreadsheet ID from URL: https://docs.google.com/spreadsheets/d/{spreadsheetId}/edit"
    },
    "range": {
      "type": "string",
      "description": "A1 notation range to read, e.g. 'Sheet1!A1:D20'. Defaults to 'A1:Z1000'."
    },
    "valueRenderOption": {
      "type": "string",
      "enum": ["FORMATTED_VALUE", "UNFORMATTED_VALUE", "FORMULA"],
      "description": "How values should be represented in the output."
    }
  },
  "additionalProperties": false
}
